psshiva_python_functions/__init__.py
psshiva_python_functions/algorithms/__init__.py
psshiva_python_functions/algorithms/sql_ai_converser/__init__.py
psshiva_python_functions/algorithms/sql_ai_converser/openai_connector.py
psshiva_python_functions-0.0.7.dist-info/METADATA
psshiva_python_functions-0.0.7.dist-info/WHEEL
psshiva_python_functions-0.0.7.dist-info/top_level.txt
psshiva_python_functions-0.0.7.dist-info/RECORD
